<?xml version="1.0" encoding="UTF-8"?>
<!DOCTYPE mapper PUBLIC "-//mybatis.org//DTD Mapper 3.0//EN" "http://mybatis.org/dtd/mybatis-3-mapper.dtd">
<mapper namespace="com.network.monitor.mapper.TrafficMonitorMapper">

    <resultMap id="BaseResultMap" type="com.network.monitor.entity.TrafficMonitorEntity">
        <id column="id" property="id"/>
        <result column="traffic_id" property="trafficId"/>
        <result column="event_id" property="eventId"/>
        <result column="request_time" property="requestTime"/>
        <result column="source_ip" property="sourceIp"/>
        <result column="target_ip" property="targetIp"/>
        <result column="source_port" property="sourcePort"/>
        <result column="target_port" property="targetPort"/>
        <result column="http_method" property="httpMethod"/>
        <result column="protocol" property="protocol"/>
        <result column="request_uri" property="requestUri"/>
        <result column="query_params" property="queryParams"/>
        <result column="request_headers" property="requestHeaders"/>
        <result column="request_body" property="requestBody"/>
        <result column="response_status" property="responseStatus"/>
        <result column="response_body" property="responseBody"/>
        <result column="response_time" property="responseTime"/>
        <result column="content_type" property="contentType"/>
        <result column="user_agent" property="userAgent"/>
        <result column="cookie" property="cookie"/>
        <result column="request_count" property="requestCount"/>
        <result column="state_tag" property="stateTag"/>
        <result column="state_value" property="stateValue"/>
        <result column="confidence" property="confidence"/>
        <result column="is_aggregated" property="isAggregated"/>
        <result column="aggregate_start_time" property="aggregateStartTime"/>
        <result column="aggregate_end_time" property="aggregateEndTime"/>
        <result column="error_count" property="errorCount"/>
        <result column="avg_processing_time" property="avgProcessingTime"/>
        <result column="create_time" property="createTime"/>
        <result column="update_time" property="updateTime"/>
    </resultMap>

    <sql id="Base_Column_List">
        id, traffic_id, event_id, request_time, source_ip, target_ip, source_port, target_port, http_method, protocol,
        request_uri, query_params, request_headers, request_body, response_status, 
        response_body, response_time, content_type, user_agent, cookie, 
        request_count, state_tag, state_value, confidence, is_aggregated, aggregate_start_time, aggregate_end_time, 
        error_count, avg_processing_time, create_time, update_time
    </sql>

    <insert id="insert" parameterType="com.network.monitor.entity.TrafficMonitorEntity" useGeneratedKeys="true" keyProperty="id">
        INSERT INTO sys_traffic_monitor (
            traffic_id, event_id, request_time, source_ip, target_ip, source_port, target_port, http_method, protocol,
            request_uri, query_params, request_headers, request_body, response_status,
            response_body, response_time, content_type, user_agent, cookie, 
            request_count, state_tag, state_value, confidence, is_aggregated, aggregate_start_time, aggregate_end_time,
            error_count, avg_processing_time, create_time, update_time
        ) VALUES (
            #{trafficId}, #{eventId}, #{requestTime}, #{sourceIp}, #{targetIp}, #{sourcePort}, #{targetPort}, #{httpMethod}, #{protocol},
            #{requestUri}, #{queryParams}, #{requestHeaders}, #{requestBody}, #{responseStatus},
            #{responseBody}, #{responseTime}, #{contentType}, #{userAgent}, #{cookie},
            #{requestCount}, #{stateTag}, #{stateValue}, #{confidence}, #{isAggregated}, #{aggregateStartTime}, #{aggregateEndTime},
            #{errorCount}, #{avgProcessingTime}, #{createTime}, #{updateTime}
        )
    </insert>

    <select id="selectById" resultMap="BaseResultMap">
        SELECT <include refid="Base_Column_List"/>
        FROM sys_traffic_monitor
        WHERE id = #{id}
    </select>

    <select id="selectByCondition" resultMap="BaseResultMap">
        SELECT <include refid="Base_Column_List"/>
        FROM sys_traffic_monitor
        <where>
            <if test="sourceIp != null and sourceIp != ''">
                AND source_ip LIKE CONCAT('%', #{sourceIp}, '%')
            </if>
            <if test="targetIp != null and targetIp != ''">
                AND target_ip LIKE CONCAT('%', #{targetIp}, '%')
            </if>
            <if test="httpMethod != null and httpMethod != ''">
                AND http_method = #{httpMethod}
            </if>
            <if test="requestUri != null and requestUri != ''">
                AND request_uri LIKE CONCAT('%', #{requestUri}, '%')
            </if>
            <if test="startTime != null">
                AND request_time &gt;= #{startTime}
            </if>
            <if test="endTime != null">
                AND request_time &lt;= #{endTime}
            </if>
        </where>
        <choose>
            <when test="orderBy != null and orderBy != ''">
                ORDER BY ${orderBy}
            </when>
            <otherwise>
                ORDER BY id DESC
            </otherwise>
        </choose>
        LIMIT #{offset}, #{limit}
    </select>

    <select id="countByCondition" resultType="long">
        SELECT COUNT(*)
        FROM sys_traffic_monitor
        <where>
            <if test="sourceIp != null and sourceIp != ''">
                AND source_ip LIKE CONCAT('%', #{sourceIp}, '%')
            </if>
            <if test="targetIp != null and targetIp != ''">
                AND target_ip LIKE CONCAT('%', #{targetIp}, '%')
            </if>
            <if test="httpMethod != null and httpMethod != ''">
                AND http_method = #{httpMethod}
            </if>
            <if test="requestUri != null and requestUri != ''">
                AND request_uri LIKE CONCAT('%', #{requestUri}, '%')
            </if>
            <if test="startTime != null">
                AND request_time &gt;= #{startTime}
            </if>
            <if test="endTime != null">
                AND request_time &lt;= #{endTime}
            </if>
        </where>
    </select>

    <select id="sumRequestCountByCondition" resultType="long">
        SELECT COALESCE(SUM(request_count), 0)
        FROM sys_traffic_monitor
        <where>
            <if test="sourceIp != null and sourceIp != ''">
                AND source_ip LIKE CONCAT('%', #{sourceIp}, '%')
            </if>
            <if test="targetIp != null and targetIp != ''">
                AND target_ip LIKE CONCAT('%', #{targetIp}, '%')
            </if>
            <if test="httpMethod != null and httpMethod != ''">
                AND http_method = #{httpMethod}
            </if>
            <if test="requestUri != null and requestUri != ''">
                AND request_uri LIKE CONCAT('%', #{requestUri}, '%')
            </if>
            <if test="startTime != null">
                AND request_time &gt;= #{startTime}
            </if>
            <if test="endTime != null">
                AND request_time &lt;= #{endTime}
            </if>
        </where>
    </select>

    <delete id="deleteById">
        DELETE FROM sys_traffic_monitor WHERE id = #{id}
    </delete>

    <insert id="batchInsert">
        INSERT INTO sys_traffic_monitor (
            traffic_id, request_time, source_ip, target_ip, source_port, target_port, http_method, protocol,
            request_uri, query_params, request_headers, request_body, response_status,
            response_body, response_time, content_type, user_agent, cookie, 
            request_count, state_tag, state_value, confidence, is_aggregated, aggregate_start_time, aggregate_end_time,
            error_count, avg_processing_time, create_time, update_time
        ) VALUES
        <foreach collection="list" item="item" separator=",">
            (#{item.trafficId}, #{item.requestTime}, #{item.sourceIp}, #{item.targetIp}, #{item.sourcePort}, #{item.targetPort}, #{item.httpMethod}, #{item.protocol},
            #{item.requestUri}, #{item.queryParams}, #{item.requestHeaders}, #{item.requestBody}, #{item.responseStatus},
            #{item.responseBody}, #{item.responseTime}, #{item.contentType}, #{item.userAgent}, #{item.cookie},
            #{item.requestCount}, #{item.stateTag}, #{item.stateValue}, #{item.confidence}, #{item.isAggregated}, #{item.aggregateStartTime}, #{item.aggregateEndTime},
            #{item.errorCount}, #{item.avgProcessingTime}, #{item.createTime}, #{item.updateTime})
        </foreach>
    </insert>

    <!-- 按小时统计流量 -->
    <select id="countHourlyTraffic" resultType="com.network.monitor.mapper.TrafficMonitorMapper$HourlyStat">
        SELECT 
            DATE_FORMAT(request_time, '%Y-%m-%d %H:00') as time,
            COALESCE(SUM(request_count), 0) as count
        FROM sys_traffic_monitor
        WHERE request_time &gt;= #{startTime}
        AND request_time &lt;= #{endTime}
        GROUP BY DATE_FORMAT(request_time, '%Y-%m-%d %H:00')
        ORDER BY time ASC
    </select>

    <!-- 按指定时间间隔统计流量 -->
    <select id="countByTimeInterval" resultType="com.network.monitor.mapper.TrafficMonitorMapper$TimeStat">
        SELECT 
            CASE 
                WHEN #{intervalMinutes} >= 1440 THEN DATE_FORMAT(request_time, '%Y-%m-%d')
                WHEN #{intervalMinutes} >= 60 THEN DATE_FORMAT(request_time, '%Y-%m-%d %H:00')
                ELSE CONCAT(
                    DATE_FORMAT(request_time, '%Y-%m-%d %H:'),
                    LPAD(FLOOR(MINUTE(request_time) / #{intervalMinutes}) * #{intervalMinutes}, 2, '0')
                )
            END as time,
            COALESCE(SUM(request_count), 0) as count
        FROM sys_traffic_monitor
        WHERE request_time &gt;= #{startTime}
        AND request_time &lt;= #{endTime}
        GROUP BY 
            CASE 
                WHEN #{intervalMinutes} >= 1440 THEN DATE_FORMAT(request_time, '%Y-%m-%d')
                WHEN #{intervalMinutes} >= 60 THEN DATE_FORMAT(request_time, '%Y-%m-%d %H:00')
                ELSE CONCAT(
                    DATE_FORMAT(request_time, '%Y-%m-%d %H:'),
                    LPAD(FLOOR(MINUTE(request_time) / #{intervalMinutes}) * #{intervalMinutes}, 2, '0')
                )
            END
        ORDER BY time ASC
    </select>
</mapper>
